eduai_friction/__init__.py
eduai_friction/main.py
eduai_friction/prompts.py
eduai_friction-2025.12.21185626.dist-info/METADATA
eduai_friction-2025.12.21185626.dist-info/WHEEL
eduai_friction-2025.12.21185626.dist-info/top_level.txt
eduai_friction-2025.12.21185626.dist-info/RECORD
