Metadata-Version: 2.4
Name: eduai-friction
Version: 2025.12.21185626
Summary: eduai-friction is a package promoting informed discussions around AI in education by analyzing 'Four Frictions' and providing actionable steps.
Author-email: eduai-friction <hi@eugene.plus>
License: MIT
Project-URL: Homepage, https://github.com/chigwell/eduai-friction
Requires-Python: >=3.9
Requires-Dist: langchain-llm7>=0.0.0
Requires-Dist: llmatch-messages>=0.0.0
Requires-Dist: langchain-core>=0.3.0
